{
  "project": "fr.wikipedia.org",
  "domain": "fr.wikipedia.org",
  "url": "https:\/\/fr.wikipedia.org\/",
  "api": "https:\/\/fr.wikipedia.org\/w\/api.php",
  "database": "frwiki",
  "namespaces": {
    "0": "",
    "1": "Discussion",
    "2": "Utilisateur",
    "3": "Discussion utilisateur",
    "4": "Wikip\u00e9dia",
    "5": "Discussion Wikip\u00e9dia",
    "6": "Fichier",
    "7": "Discussion fichier",
    "8": "MediaWiki",
    "9": "Discussion MediaWiki",
    "10": "Mod\u00e8le",
    "11": "Discussion mod\u00e8le",
    "12": "Aide",
    "13": "Discussion aide",
    "14": "Cat\u00e9gorie",
    "15": "Discussion cat\u00e9gorie",
    "100": "Portail",
    "101": "Discussion Portail",
    "102": "Projet",
    "103": "Discussion Projet",
    "104": "R\u00e9f\u00e9rence",
    "105": "Discussion R\u00e9f\u00e9rence",
    "710": "TimedText",
    "711": "TimedText talk",
    "828": "Module",
    "829": "Discussion module",
    "2300": "Gadget",
    "2301": "Discussion gadget",
    "2302": "D\u00e9finition de gadget",
    "2303": "Discussion d\u00e9finition de gadget",
    "2600": "Sujet"
  },
  "elapsed_time": 0.013
}
